[
    {
        "Giá T10\/22":32.9,
        "Giá T11\/22":32.9,
        "Giá T12\/22":32.9,
        "Giá T1\/23":32.1,
        "Giá T2\/23":32.1,
        "Giá T3\/23":32.1,
        "Giá T4\/23":32.9,
        "Giá T5\/23":32.9,
        "Giá T6\/23":32.9,
        "Giá T7\/23":31.1,
        "Giá T8\/23":31.1,
        "Giá T9\/23":31.1,
        "Giá T10\/23":34.8,
        "Giá T11\/23":34.8,
        "Giá T12\/23":34.8,
        "Giá T1\/24":34.8,
        "Giá T2\/24":34.8,
        "Giá T3\/24":34.8,
        "Giá T4\/24":47.1,
        "Giá T5\/24":47.1,
        "Giá T6\/24":47.1,
        "Giá T7\/24":48.6,
        "Giá T8\/24":48.6,
        "Giá T9\/24":48.6,
        "Giá T10\/24":48.6,
        "Giá T11\/24":48.2
    },
    {
        "Giá T10\/22":35.3,
        "Giá T11\/22":35.3,
        "Giá T12\/22":35.3,
        "Giá T1\/23":34.3,
        "Giá T2\/23":34.3,
        "Giá T3\/23":34.3,
        "Giá T4\/23":36.3,
        "Giá T5\/23":36.3,
        "Giá T6\/23":36.3,
        "Giá T7\/23":37.1,
        "Giá T8\/23":37.1,
        "Giá T9\/23":37.1,
        "Giá T10\/23":40.7,
        "Giá T11\/23":40.7,
        "Giá T12\/23":40.7,
        "Giá T1\/24":40.7,
        "Giá T2\/24":40.7,
        "Giá T3\/24":40.7,
        "Giá T4\/24":50.7,
        "Giá T5\/24":50.7,
        "Giá T6\/24":50.7,
        "Giá T7\/24":54.6,
        "Giá T8\/24":54.6,
        "Giá T9\/24":54.6,
        "Giá T10\/24":54.6,
        "Giá T11\/24":54.81
    },
    {
        "Giá T10\/22":41.4,
        "Giá T11\/22":41.4,
        "Giá T12\/22":41.4,
        "Giá T1\/23":39.1,
        "Giá T2\/23":39.1,
        "Giá T3\/23":39.1,
        "Giá T4\/23":38.1,
        "Giá T5\/23":38.1,
        "Giá T6\/23":38.1,
        "Giá T7\/23":37.8,
        "Giá T8\/23":37.8,
        "Giá T9\/23":37.8,
        "Giá T10\/23":42.8,
        "Giá T11\/23":42.8,
        "Giá T12\/23":42.8,
        "Giá T1\/24":42.8,
        "Giá T2\/24":42.8,
        "Giá T3\/24":42.8,
        "Giá T4\/24":54.4,
        "Giá T5\/24":54.4,
        "Giá T6\/24":54.4,
        "Giá T7\/24":58.3,
        "Giá T8\/24":58.3,
        "Giá T9\/24":58.3,
        "Giá T10\/24":58.3,
        "Giá T11\/24":57.07
    }
]